aio_task/__init__.py
aio_task/_version.py
aio_task/broker.py
aio_task/errors.py
aio_task/task.py
aio_task/utils.py
aio_task/worker.py
aio_task/cache/__init__.py
aio_task/cache/base.py
aio_task/cache/dummy.py
aio_task/cache/redis.py
aio_task/cache/sentinel.py
aio_task/queue/__init__.py
aio_task/queue/base.py
aio_task/queue/dummy.py
aio_task/queue/rabbitmq.py
tests/integration/__init__.py
tests/integration/cache/__init__.py
tests/integration/cache/test_base.py
tests/integration/queue/__init__.py
tests/integration/queue/test_base.py
tests/unit/__init__.py
tests/unit/test_broker.py
tests/unit/test_worker.py
aio_task-1.1.0.dist-info/LICENSE.txt
aio_task-1.1.0.dist-info/METADATA
aio_task-1.1.0.dist-info/WHEEL
aio_task-1.1.0.dist-info/top_level.txt
aio_task-1.1.0.dist-info/RECORD
