Metadata-Version: 2.1
Name: aio-task
Version: 1.1.0
Summary: A simple and reliable tasks manager. Attempt for a celery like, asyncio friendly.
Home-page: https://cdlr75.gitlab.io/aio-task/
Author: cdlr75
Author-email: cdlr75@gmail.com
License: UNKNOWN
Project-URL: Bug Reports, https://gitlab.com/cdlr75/aio-task/issues
Project-URL: Source, https://gitlab.com/cdlr75/aio-task/
Keywords: asyncio asynchronous tasks broker celery
Platform: UNKNOWN
Classifier: Development Status :: 4 - Beta
Classifier: Intended Audience :: Developers
Classifier: Topic :: Software Development :: Build Tools
Classifier: License :: OSI Approved :: Apache Software License
Classifier: Programming Language :: Python :: 3.6
Classifier: Programming Language :: Python :: 3.7
Requires-Python: >=3.6
Requires-Dist: aioredis (==1.3.0)
Requires-Dist: aio-pika (==6.1.2)
Provides-Extra: doc
Requires-Dist: sphinx ; extra == 'doc'
Requires-Dist: recommonmark ; extra == 'doc'
Requires-Dist: changelogfromtags ; extra == 'doc'
Provides-Extra: test
Requires-Dist: asynctest ; extra == 'test'
Requires-Dist: pytest ; extra == 'test'
Requires-Dist: pytest-cov ; extra == 'test'
